astrocyte/__init__.py
astrocyte/api.py
astrocyte/cli.py
astrocyte/exceptions.py
astrocyte/templates.py
astrocyte/templates/README.md.txt
astrocyte/templates/__init__.py.txt
astrocyte/templates/_gitignore.txt
astrocyte/templates/setup.py.txt
astrocyte-0.2.3.data/data/templates/README.md.txt
astrocyte-0.2.3.data/data/templates/__init__.py.txt
astrocyte-0.2.3.data/data/templates/_gitignore.txt
astrocyte-0.2.3.data/data/templates/setup.py.txt
astrocyte-0.2.3.dist-info/LICENSE
astrocyte-0.2.3.dist-info/METADATA
astrocyte-0.2.3.dist-info/WHEEL
astrocyte-0.2.3.dist-info/entry_points.txt
astrocyte-0.2.3.dist-info/top_level.txt
astrocyte-0.2.3.dist-info/RECORD
