Metadata-Version: 2.1
Name: astrocyte
Version: 0.2.3
Summary: Packager for Glia
Home-page: https://github.com/dbbs-lab/astrocyte
Author: Robin De Schepper
Author-email: robingilbert.deschepper@unipv.it
License: GPLv3
Platform: UNKNOWN
Classifier: Programming Language :: Python :: 3
Classifier: Operating System :: OS Independent
Requires-Dist: nrn-glia (>=0.1.8)
Requires-Dist: setuptools
Requires-Dist: gitpython (>=3.0.0)
Requires-Dist: twine (>=3.0.0)
Requires-Dist: requests
Requires-Dist: appdirs (>=1.4.3)
